grades_report/__init__.py
grades_report/__version__.py
grades_report/cli.py
grades_report/parsing.py
grades_report/stats.py
tests/__init__.py
tests/integrations/__init__.py
tests/integrations/test_cli.py
tests/unit/__init__.py
tests/unit/grades_report/__init__.py
tests/unit/grades_report/test_parsing.py
tests/unit/grades_report/test_stats.py
grades_report-0.0.2.dist-info/LICENSE
grades_report-0.0.2.dist-info/METADATA
grades_report-0.0.2.dist-info/WHEEL
grades_report-0.0.2.dist-info/entry_points.txt
grades_report-0.0.2.dist-info/top_level.txt
grades_report-0.0.2.dist-info/RECORD
