Metadata-Version: 2.1
Name: grades-report
Version: 0.0.2
Summary: Get info and stats about grades
Home-page: https://github.com/KAUTH/grades-report
Author: KAUTH
Author-email: konpap1996@hotmail.com
License: MIT
Project-URL: Source, https://github.com/KAUTH/grades-report
Platform: UNKNOWN
Classifier: License :: OSI Approved :: MIT License
Classifier: Natural Language :: English
Classifier: Operating System :: OS Independent
Classifier: Programming Language :: Python
Classifier: Programming Language :: Python :: 3
Classifier: Programming Language :: Python :: 3.7
Classifier: Programming Language :: Python :: Implementation :: PyPy
Classifier: Topic :: Education
Requires-Python: >=3.7
Requires-Dist: markdown
Requires-Dist: click (>=7.1.2)
